pymatunits/__init__.py
pymatunits/mat_prop.py
pymatunits/units.py
pymatunits/utils.py
pymatunits-1.5.dist-info/licenses/LICENSE.md
pymatunits-1.5.dist-info/METADATA
pymatunits-1.5.dist-info/WHEEL
pymatunits-1.5.dist-info/top_level.txt
pymatunits-1.5.dist-info/RECORD
