Metadata-Version: 2.4
Name: pymatunits
Version: 1.5
Summary: Python utilities, including material definition and unit system handling with pint
Author-email: Adam Cox <adam.cox@asdl.gatech.edu>
License: # GNU LESSER GENERAL PUBLIC LICENSE
Project-URL: Repository, https://github.gatech.edu/acox37/pymatunits
Project-URL: Issues, https://github.gatech.edu/acox37/pymatunits/issues
Requires-Python: >=3.5
License-File: LICENSE.md
Requires-Dist: numpy
Requires-Dist: pandas
Requires-Dist: pint
Requires-Dist: mkdocs
Dynamic: license-file
